COPYING
MANIFEST.in
README.rst
buildout.cfg
requirements.txt
setup.py
version.txt
bob/__init__.py
bob.pad.vein.egg-info/PKG-INFO
bob.pad.vein.egg-info/SOURCES.txt
bob.pad.vein.egg-info/dependency_links.txt
bob.pad.vein.egg-info/entry_points.txt
bob.pad.vein.egg-info/requires.txt
bob.pad.vein.egg-info/top_level.txt
bob/pad/__init__.py
bob/pad/vein/__init__.py
bob/pad/vein/test_databases.py
bob/pad/vein/algorithm/__init__.py
bob/pad/vein/algorithm/noop.py
bob/pad/vein/configurations/__init__.py
bob/pad/vein/configurations/fourier.py
bob/pad/vein/configurations/gridio4g48.py
bob/pad/vein/configurations/parallel.py
bob/pad/vein/configurations/verafinger.py
bob/pad/vein/database/__init__.py
bob/pad/vein/database/verafinger.py
bob/pad/vein/extractor/__init__.py
bob/pad/vein/extractor/fourier.py
bob/pad/vein/preprocessor/__init__.py
bob/pad/vein/preprocessor/histoeq.py
doc/api.rst
doc/baselines.rst
doc/index.rst
doc/links.rst
doc/references.rst
doc/resources.rst
doc/img/favicon.ico
doc/img/logo.png