Metadata-Version: 1.2
Name: bob.pad.vein
Version: 1.0.0
Summary: Implements tools for spoofing or presentation attack detection in vein biometrics
Home-page: https://gitlab.idiap.ch/bob/bob.pad.vein
Author: Pedro Tome
Author-email: pedro.tome@idiap.ch
Maintainer: Andre Anjos
Maintainer-email: andre.anjos@idiap.ch
License: GPLv3
Keywords: bob
Platform: UNKNOWN
Classifier: Framework :: Bob
Classifier: Development Status :: 3 - Alpha
Classifier: Intended Audience :: Developers
Classifier: License :: OSI Approved :: GNU General Public License v3 (GPLv3)
Classifier: Natural Language :: English
Classifier: Programming Language :: Python
Classifier: Topic :: Scientific/Engineering :: Artificial Intelligence
